ump/__init__.py
ump/bill.py
ump/checker.py
ump/cleaner.py
ump/constants.py
ump/log.py
ump/reader.py
ump/six.py
ump/uploader.py
ump/utils.py
ump/worker.py
ump/writer.py
ump-0.2.4.data/scripts/umpctl
ump-0.2.4.dist-info/METADATA
ump-0.2.4.dist-info/WHEEL
ump-0.2.4.dist-info/top_level.txt
ump-0.2.4.dist-info/RECORD
