Metadata-Version: 2.1
Name: ump
Version: 0.2.4
Summary: upload data safer
Home-page: https://github.com/dantezhu/ump
Author: dantezhu
Author-email: dantezhu <zny2008@gmail.com>
License: MIT
Project-URL: Homepage, https://github.com/dantezhu/ump
Platform: any
Requires-Dist: redis
Requires-Dist: click
Requires-Dist: setproctitle
Requires-Dist: netkit
